{
  "133977151": {
    "name": "オッケークーゲル",
    "fan": 1075161343,
    "circle_name": "はしる団",
    "ts": "20251231",
    "viewer_id": 133977151,
    "comment": "よろしくお願いします",
    "rank_score": 14803465,
    "circle_id": 243807865
  },
  "825827749": {
    "name": "rt",
    "fan": 703217162,
    "circle_name": "123",
    "ts": "20251231",
    "viewer_id": 825827749,
    "comment": "123",
    "rank_score": 17903917,
    "circle_id": 691769629
  },
  "135604918": {
    "name": "淡島",
    "fan": 499086015,
    "circle_name": "異次元の逃亡者",
    "ts": "20251231",
    "viewer_id": 135604918,
    "comment": "よろしくお願いします",
    "rank_score": 13036933,
    "circle_id": 790156146
  },
  "177451574": {
    "name": "なな",
    "fan": 594123527,
    "circle_name": "無言ok出入り自由",
    "ts": "20251231",
    "viewer_id": 177451574,
    "comment": "O",
    "rank_score": 18890960,
    "circle_id": 132571369
  },
  "233306038": {
    "name": "ルプサーダ",
    "fan": 2733376554,
    "circle_name": "イジツ華劇団★風組",
    "ts": "20251231",
    "viewer_id": 233306038,
    "comment": "変更日2025／12／29　パワ9長9ダンスセイちゃん、右回り・冬目覚め・長距離遺伝子・",
    "rank_score": 23921187,
    "circle_id": 987887252
  },
  "239614006": {
    "name": "とっとり鳥の助",
    "fan": 1272304381,
    "circle_name": "トレセン学園",
    "ts": "20251231",
    "viewer_id": 239614006,
    "comment": "エイシンフラッシュきたー",
    "rank_score": 19653670,
    "circle_id": 582594018
  },
  "167902902": {
    "name": "駆け出し",
    "fan": 59475821,
    "circle_name": "気ままな",
    "ts": "20251231",
    "viewer_id": 167902902,
    "comment": "よろしくお願いします",
    "rank_score": 2209076,
    "circle_id": 483132915
  },
  "184414006": {
    "name": "DTMer",
    "fan": 393570422,
    "circle_name": "まったり牧場",
    "ts": "20251231",
    "viewer_id": 184414006,
    "comment": "マイブームは筋トレ",
    "rank_score": 12690402,
    "circle_id": 482811488
  },
  "162875702": {
    "name": "ラブチキン",
    "fan": 651310516,
    "circle_name": "テイオーすてっぷ",
    "ts": "20251231",
    "viewer_id": 162875702,
    "comment": "まったり",
    "rank_score": 5564575,
    "circle_id": 435350647
  },
  "185157174": {
    "name": "羽乃音",
    "fan": 3274980664,
    "circle_name": "BOOKER’S",
    "ts": "20251231",
    "viewer_id": 185157174,
    "comment": "月3－４000万程度のマッタリ勢ですが、よろしくお願いします～　＞ヮ＜",
    "rank_score": 16741471,
    "circle_id": 163028432
  },
  "110312758": {
    "name": "らり吉",
    "fan": 3164577,
    "circle_name": "",
    "ts": "20251231",
    "viewer_id": 110312758,
    "comment": "よろしくお願いします",
    "rank_score": 709691
  },
  "172118582": {
    "name": "ケシャヴ",
    "fan": 971057698,
    "circle_name": "ニンジン畑",
    "ts": "20251231",
    "viewer_id": 172118582,
    "comment": "はわわわわわわ",
    "rank_score": 14213785,
    "circle_id": 236457687
  },
  "152890120": {
    "name": "やつちん",
    "fan": 1919834160,
    "circle_name": "riceshower",
    "ts": "20251231",
    "viewer_id": 152890120,
    "comment": "よろしくお願いします",
    "rank_score": 13685395,
    "circle_id": 767825201
  },
  "224612232": {
    "name": "菅義偉",
    "fan": 2240284709,
    "circle_name": "全角地方",
    "ts": "20251231",
    "viewer_id": 224612232,
    "comment": "よろしくお願いします",
    "rank_score": 10464440,
    "circle_id": 628504359
  },
  "130986632": {
    "name": "おだびー",
    "fan": 1370432648,
    "circle_name": "おだーず",
    "ts": "20251231",
    "viewer_id": 130986632,
    "comment": "よろしくお願いします",
    "rank_score": 17199803,
    "circle_id": 736076463
  },
  "181098760": {
    "name": "あーるたかたか",
    "fan": 3541387041,
    "circle_name": "ぱかぱか",
    "ts": "20251231",
    "viewer_id": 181098760,
    "comment": "スタ3パワ6　長距離9　白因子80個　先行用",
    "rank_score": 31385440,
    "circle_id": 652604118
  },
  "111558152": {
    "name": "いぶ",
    "fan": 76519533,
    "circle_name": "",
    "ts": "20251231",
    "viewer_id": 111558152,
    "comment": "めじろ！",
    "rank_score": 3272972
  },
  "111323272": {
    "name": "みぃしゃ",
    "fan": 1818656514,
    "circle_name": "建御雷神",
    "ts": "20251231",
    "viewer_id": 111323272,
    "comment": "王とその騎バの違いは何だ？人とウマ娘じゃねぇ、本能だ！（長星8スピ9）",
    "rank_score": 14222761,
    "circle_id": 764660300
  },
  "112016392": {
    "name": "えくれあ",
    "fan": 331529464,
    "circle_name": "六甲の美味しい水",
    "ts": "20251231",
    "viewer_id": 112016392,
    "comment": "ぱないの！",
    "rank_score": 6383198,
    "circle_id": 814971115
  },
  "187221512": {
    "name": "ドゥルトレッグ",
    "fan": 797765924,
    "circle_name": "サークルヴァニア",
    "ts": "20251231",
    "viewer_id": 187221512,
    "comment": "よろしくお願いします",
    "rank_score": 15503196,
    "circle_id": 179969705
  },
  "215088136": {
    "name": "るぎ",
    "fan": 1296291473,
    "circle_name": "カノープス",
    "ts": "20251231",
    "viewer_id": 215088136,
    "comment": "よろしくお願いします",
    "rank_score": 11316413,
    "circle_id": 662100322
  },
  "178394504": {
    "name": "朱鷺",
    "fan": 499815115,
    "circle_name": "TB・Table",
    "ts": "20251231",
    "viewer_id": 178394504,
    "comment": "よろしくお願いします",
    "rank_score": 16810136,
    "circle_id": 641356749
  },
  "142067573": {
    "name": "こゆっきー",
    "fan": 113195656,
    "circle_name": "",
    "ts": "20251231",
    "viewer_id": 142067573,
    "comment": "よろしくお願いします",
    "rank_score": 3456535
  },
  "135111925": {
    "name": "夜勤",
    "fan": 801637404,
    "circle_name": "単位数え隊",
    "ts": "20251231",
    "viewer_id": 135111925,
    "comment": "よろしくお願いします",
    "rank_score": 17834505,
    "circle_id": 822746976
  },
  "125166453": {
    "name": "ふく3104",
    "fan": 797680044,
    "circle_name": "ウマ娘靴流通センター",
    "ts": "20251231",
    "viewer_id": 125166453,
    "comment": "よろしくお願いします",
    "rank_score": 18713563,
    "circle_id": 112925383
  },
  "114509941": {
    "name": "EXID",
    "fan": 1496017080,
    "circle_name": "LEGGO",
    "ts": "20251231",
    "viewer_id": 114509941,
    "comment": "よろしくお願いします",
    "rank_score": 27267169,
    "circle_id": 725483867
  },
  "114507893": {
    "name": "タカヒロ",
    "fan": 378938680,
    "circle_name": "レオパーず",
    "ts": "20251231",
    "viewer_id": 114507893,
    "comment": "よろしくお願いします",
    "rank_score": 15609155,
    "circle_id": 610412948
  },
  "226108917": {
    "name": "たまごのきわみ",
    "fan": 519375555,
    "circle_name": "美浦トレセン学園",
    "ts": "20251231",
    "viewer_id": 226108917,
    "comment": "復帰勢",
    "rank_score": 9695882,
    "circle_id": 331638550
  },
  "237415285": {
    "name": "ルナアロエ",
    "fan": 276695384,
    "circle_name": "お気軽屋",
    "ts": "20251231",
    "viewer_id": 237415285,
    "comment": "よろしくお願いします",
    "rank_score": 9654947,
    "circle_id": 393393544
  },
  "158222581": {
    "name": "トレィナァ",
    "fan": 16790088,
    "circle_name": "子猫倶楽部",
    "ts": "20251231",
    "viewer_id": 158222581,
    "comment": "よろしくお願いします",
    "rank_score": 2310378,
    "circle_id": 861453923
  },
  "200714997": {
    "name": "ニケ",
    "fan": 2691880732,
    "circle_name": "びよんど",
    "ts": "20251231",
    "viewer_id": 200714997,
    "comment": "ミライドンは　エレキフィールドを　はり　未来の機関を　躍動させる！！",
    "rank_score": 10782756,
    "circle_id": 159463034
  },
  "140519541": {
    "name": "ウマ女良",
    "fan": 3987123057,
    "circle_name": "野良とれぇなぁ",
    "ts": "20251231",
    "viewer_id": 140519541,
    "comment": "あたしさぁ　10cmくらいなら　　　浮けるんだぜ？　",
    "rank_score": 25175718,
    "circle_id": 656578613
  },
  "111435919": {
    "name": "イエナガ",
    "fan": 40846233,
    "circle_name": "HEI　Kei",
    "ts": "20251231",
    "viewer_id": 111435919,
    "comment": "よろしくお願いします",
    "rank_score": 4388244,
    "circle_id": 346551072
  },
  "196101647": {
    "name": "Maru",
    "fan": 403211324,
    "circle_name": "Dandelion",
    "ts": "20251231",
    "viewer_id": 196101647,
    "comment": "よろしくお願いします",
    "rank_score": 11618820,
    "circle_id": 271563579
  },
  "229942415": {
    "name": "ロード",
    "fan": 1739677867,
    "circle_name": "ミドリ牧場",
    "ts": "20251231",
    "viewer_id": 229942415,
    "comment": "よろしくお願いします",
    "rank_score": 17415459,
    "circle_id": 898419948
  },
  "131828367": {
    "name": "すだのら",
    "fan": 2160923743,
    "circle_name": "桜組",
    "ts": "20251231",
    "viewer_id": 131828367,
    "comment": "えい、えい、むん！",
    "rank_score": 23837165,
    "circle_id": 849255408
  },
  "166976911": {
    "name": "わんこ",
    "fan": 1542571259,
    "circle_name": "スピードの向こう側",
    "ts": "20251231",
    "viewer_id": 166976911,
    "comment": "よろしくお願いします",
    "rank_score": 30758190,
    "circle_id": 338808261
  },
  "227457295": {
    "name": "大貴族連合",
    "fan": 1222967948,
    "circle_name": "うまぴょいちゃまちゅ",
    "ts": "20251231",
    "viewer_id": 227457295,
    "comment": "よろしくお願いします",
    "rank_score": 11659325,
    "circle_id": 110294255
  },
  "171705615": {
    "name": "ひな",
    "fan": 679345272,
    "circle_name": "（ΦωΦ）",
    "ts": "20251231",
    "viewer_id": 171705615,
    "comment": "ド",
    "rank_score": 17680706,
    "circle_id": 214614587
  },
  "147956367": {
    "name": "旨旨馬",
    "fan": 5861162,
    "circle_name": "",
    "ts": "20251231",
    "viewer_id": 147956367,
    "comment": "よろしくお願いします",
    "rank_score": 949980
  },
  "121130161": {
    "name": "海老冢智",
    "fan": 945476420,
    "circle_name": "魔結社2会",
    "ts": "20251231",
    "viewer_id": 121130161,
    "comment": "死了",
    "rank_score": 11376519,
    "circle_id": 391405678
  },
  "124460894": {
    "name": "阿兔p",
    "fan": 730016756,
    "circle_name": "魔結社2会",
    "ts": "20251231",
    "viewer_id": 124460894,
    "comment": "lucky",
    "rank_score": 16599950,
    "circle_id": 391405678
  },
  "128221089": {
    "name": "アキ",
    "fan": 1150284548,
    "circle_name": "魔結社2会",
    "ts": "20251231",
    "viewer_id": 128221089,
    "comment": "QQQ",
    "rank_score": 17556110,
    "circle_id": 391405678
  },
  "133072199": {
    "name": "ひらさわゆい",
    "fan": 1483102654,
    "circle_name": "魔結社2会",
    "ts": "20251231",
    "viewer_id": 133072199,
    "comment": "133072199",
    "rank_score": 11155316,
    "circle_id": 391405678
  },
  "211777913": {
    "name": "Moregrey",
    "fan": 443838588,
    "circle_name": "魔結社2会",
    "ts": "20251231",
    "viewer_id": 211777913,
    "comment": "よろしくお願いします",
    "rank_score": 8464441,
    "circle_id": 391405678
  },
  "266016587": {
    "name": "Yuki",
    "fan": 1126374251,
    "circle_name": "魔結社2会",
    "ts": "20251231",
    "viewer_id": 266016587,
    "comment": "よろしくお願いします",
    "rank_score": 7501886,
    "circle_id": 391405678
  },
  "272646586": {
    "name": "Svengalis",
    "fan": 1096607896,
    "circle_name": "魔結社2会",
    "ts": "20251231",
    "viewer_id": 272646586,
    "comment": "よろしくお願いします",
    "rank_score": 16761272,
    "circle_id": 391405678
  },
  "281608518": {
    "name": "神楽",
    "fan": 774436559,
    "circle_name": "魔結社2会",
    "ts": "20251231",
    "viewer_id": 281608518,
    "comment": "よろしくお願いします",
    "rank_score": 8276322,
    "circle_id": 391405678
  },
  "307738352": {
    "name": "MadDevil",
    "fan": 2169656300,
    "circle_name": "魔結社2会",
    "ts": "20251231",
    "viewer_id": 307738352,
    "comment": "あとで力を満たします",
    "rank_score": 12946130,
    "circle_id": 391405678
  },
  "326370783": {
    "name": "Asa",
    "fan": 3082570866,
    "circle_name": "魔結社2会",
    "ts": "20251231",
    "viewer_id": 326370783,
    "comment": "よろしくお願いします",
    "rank_score": 20739117,
    "circle_id": 391405678
  },
  "454336867": {
    "name": "ムツミ大旋風！",
    "fan": 2205880638,
    "circle_name": "魔結社2会",
    "ts": "20251231",
    "viewer_id": 454336867,
    "comment": "ライブ、楽しかった！",
    "rank_score": 17417356,
    "circle_id": 391405678
  },
  "461662005": {
    "name": "1640",
    "fan": 688713824,
    "circle_name": "魔結社2会",
    "ts": "20251231",
    "viewer_id": 461662005,
    "comment": "よろしくお願いします",
    "rank_score": 14062653,
    "circle_id": 391405678
  },
  "498849266": {
    "name": "辣条菌．",
    "fan": 929472897,
    "circle_name": "魔結社2会",
    "ts": "20251231",
    "viewer_id": 498849266,
    "comment": "ID：498849266。",
    "rank_score": 10292106,
    "circle_id": 391405678
  },
  "674870401": {
    "name": "右右",
    "fan": 1048507868,
    "circle_name": "魔結社2会",
    "ts": "20251231",
    "viewer_id": 674870401,
    "comment": "よろしくお願いします",
    "rank_score": 9206322,
    "circle_id": 391405678
  },
  "756192861": {
    "name": "weather",
    "fan": 1229453470,
    "circle_name": "魔結社2会",
    "ts": "20251231",
    "viewer_id": 756192861,
    "comment": "昔昔",
    "rank_score": 13462189,
    "circle_id": 391405678
  },
  "609295881": {
    "name": "專殺逃批",
    "fan": 359133914,
    "circle_name": "魔結社2会",
    "ts": "20251231",
    "viewer_id": 609295881,
    "comment": "NO．1　Loves　Only　You　　NO．2　Buena　Vista　　　",
    "rank_score": 12261833,
    "circle_id": 391405678
  },
  "651079298": {
    "name": "CaiSpecial",
    "fan": 4814053729,
    "circle_name": "魔結社2会",
    "ts": "20251231",
    "viewer_id": 651079298,
    "comment": "下班死魚",
    "rank_score": 15024722,
    "circle_id": 391405678
  },
  "663976787": {
    "name": "牢鷄の匠巴",
    "fan": 111439243,
    "circle_name": "魔結社2会",
    "ts": "20251231",
    "viewer_id": 663976787,
    "comment": "よろしくお願いします",
    "rank_score": 4598306,
    "circle_id": 391405678
  },
  "810420230": {
    "name": "祐樹",
    "fan": 211020249,
    "circle_name": "魔結社2会",
    "ts": "20251231",
    "viewer_id": 810420230,
    "comment": "よろしくお願いします",
    "rank_score": 2542189,
    "circle_id": 391405678
  },
  "737616560": {
    "name": "PariVision",
    "fan": 730523279,
    "circle_name": "魔結社2会",
    "ts": "20251231",
    "viewer_id": 737616560,
    "comment": "よろしくお願いします",
    "rank_score": 14113851,
    "circle_id": 391405678
  },
  "762430286": {
    "name": "柚芽",
    "fan": 1376326432,
    "circle_name": "魔結社2会",
    "ts": "20251231",
    "viewer_id": 762430286,
    "comment": "よろしくお願いします",
    "rank_score": 16310461,
    "circle_id": 391405678
  },
  "864445366": {
    "name": "零",
    "fan": 1350685023,
    "circle_name": "魔結社2会",
    "ts": "20251231",
    "viewer_id": 864445366,
    "comment": "ガチャ運最悪",
    "rank_score": 15158832,
    "circle_id": 391405678
  },
  "504794401": {
    "name": "gugugaga",
    "fan": 946521896,
    "circle_name": "魔結社2会",
    "ts": "20251231",
    "viewer_id": 504794401,
    "comment": "誰よりも華麗に、私だけのステップで！",
    "rank_score": 12417591,
    "circle_id": 391405678
  },
  "697736536": {
    "name": "千鳥舞",
    "fan": 253818391,
    "circle_name": "魔結社2会",
    "ts": "20251231",
    "viewer_id": 697736536,
    "comment": "よろしくお願いします",
    "rank_score": 4850103,
    "circle_id": 391405678
  },
  "871233599": {
    "name": "メプ茶",
    "fan": 1048063014,
    "circle_name": "魔結社2会",
    "ts": "20251231",
    "viewer_id": 871233599,
    "comment": "二度寝したいな",
    "rank_score": 12211520,
    "circle_id": 391405678
  },
  "920979498": {
    "name": "涯migiwa",
    "fan": 1761085763,
    "circle_name": "魔結社2会",
    "ts": "20251231",
    "viewer_id": 920979498,
    "comment": "寄",
    "rank_score": 20360066,
    "circle_id": 391405678
  },
  "921755732": {
    "name": "念桃ルシ",
    "fan": 493449731,
    "circle_name": "魔結社2会",
    "ts": "20251231",
    "viewer_id": 921755732,
    "comment": "よろしくお願いします",
    "rank_score": 8150524,
    "circle_id": 391405678
  },
  "924377058": {
    "name": "宇智波辣辣",
    "fan": 211606323,
    "circle_name": "魔結社2会",
    "ts": "20251231",
    "viewer_id": 924377058,
    "comment": "中国から来たロシアのナナに注目してください",
    "rank_score": 8064587,
    "circle_id": 391405678
  },
  "536610666": {
    "name": "syuhsnfh",
    "fan": 988638207,
    "circle_name": "魔結社2会",
    "ts": "20251231",
    "viewer_id": 536610666,
    "comment": "よろしくお願いします",
    "rank_score": 12874244,
    "circle_id": 391405678
  }
}